lcmlog/__init__.py
lcmlog/event.py
lcmlog/io.py
lcmlog_py-0.1.0.dist-info/WHEEL
lcmlog_py-0.1.0.dist-info/METADATA
lcmlog_py-0.1.0.dist-info/RECORD
