Metadata-Version: 2.1
Name: lcmlog-py
Version: 0.1.0
Summary: LCM log utilities
License: MIT
Author: Kevin Barnard
Author-email: kbarnard@mbari.org
Requires-Python: >=3.7,<4.0
Classifier: License :: OSI Approved :: MIT License
Classifier: Programming Language :: Python :: 3
Classifier: Programming Language :: Python :: 3.7
Classifier: Programming Language :: Python :: 3.8
Classifier: Programming Language :: Python :: 3.9
Classifier: Programming Language :: Python :: 3.10
Classifier: Programming Language :: Python :: 3.11
